{
	"name" : "Ringed Jewel",
	"semiMajorAxis" : 25000,
	"inclination" : 14,
	"primaryBody" : "SUN",
	"isMoon" : false,
	"atmoEndSize" : 500,
	"hasClouds" : true,
	"topCloudSize" : 500,
	"bottomCloudSize" : 470,
	"bottomCloudTint" : 
	{
		"r" : 181,
		"g" : 181,
		"b" : 230,
		"a" : 255
	},
	"topCloudTint" : 
	{
		"r" : 181,
		"g" : 255,
		"b" : 230,
		"a" : 255
	},
	"hasWater" : false,
	"waterSize" : 101,
	"hasRain" : false,
	"hasGravity" : true,
	"surfaceAcceleration" : 4,
	"hasMapMarker" : true,
	"hasFog" : true,
	"fogTint" : 
	{
		"r" : 255,
		"g" : 128,
		"b" : 128,
		"a" : 255
	},
	"fogDensity": 0.4,
	"fogSize": 450,
	"hasGround": false,
	"groundSize" : 100,
	"isTidallyLocked" : false,
	"lightTint" : 
	{
		"r" : 200,
		"g" : 240,
		"b" : 255,
		"a" : 255
	},
	"hasSnow" : true,
	"longitudeOfAscendingNode" : 0,
	"eccentricity" : 0,
	"argumentOfPeriapsis": 0,
	"hasRings" : true,
	"ringInnerRadius" : 800,
	"ringOuterRadius" : 950,
	"ringInclination" : 80,
	"ringLongitudeOfAscendingNode" : 30,
	"ringTexture" : "planets/assets/ringed_jewel.png",
	"hasLava" : true,
	"lavaSize" : 300,
}